setup.py
randomquote/__init__.py
randomquote.egg-info/PKG-INFO
randomquote.egg-info/SOURCES.txt
randomquote.egg-info/dependency_links.txt
randomquote.egg-info/not-zip-safe
randomquote.egg-info/top_level.txt