Metadata-Version: 1.0
Name: randomquote
Version: 1.0
Summary: Random quote
Home-page: https://github.com/darkanzali/random-quotes
Author: darkanzali
Author-email: darkanzali@outlook.com
License: MIT
Platform: UNKNOWN
